auth/__init__.py
auth/auth.py
config/__init__.py
config/config.json
config/config.py
config/flight_data.json
config/flight_dec_data.json
config/geo_data.json
server/__init__.py
server/cli.py
server/server.py
services/__init__.py
services/rid_definitions.py
services/services.py
utm_cli-0.1.11.dist-info/AUTHORS.rst
utm_cli-0.1.11.dist-info/LICENSE
utm_cli-0.1.11.dist-info/METADATA
utm_cli-0.1.11.dist-info/WHEEL
utm_cli-0.1.11.dist-info/entry_points.txt
utm_cli-0.1.11.dist-info/top_level.txt
utm_cli-0.1.11.dist-info/RECORD
